primosmd/primosmd.py
primosmd-3.0.dist-info/LICENSE
primosmd-3.0.dist-info/METADATA
primosmd-3.0.dist-info/WHEEL
primosmd-3.0.dist-info/top_level.txt
primosmd-3.0.dist-info/RECORD
