Metadata-Version: 2.1
Name: primosmd
Version: 3.0
Summary: Funcion numeros primos
Home-page: UNKNOWN
Author: mariodominguezcarnal@MacBook-Air-de-Mario
Author-email: mdominguezcarnal@gmail.com
License: GNU GPLv3
Keywords: numeros primos,matematicas
Platform: UNKNOWN
Classifier: Development Status :: 4 - Beta
Classifier: Intended Audience :: Developers
Classifier: Topic :: Utilities
Classifier: License :: OSI Approved :: GNU General Public License v3 (GPLv3)
Classifier: Programming Language :: Python :: 3
Classifier: Operating System :: OS Independent
